speech_server/__init__.py
speech_server/common/base_tts_config.py
speech_server/common/base_tts_service.py
speech_server/server/app.py
speech_server/server/config.py
speech_server/server/logger.py
speech_server/server/models.py
speech_server/tts_services/chatter_box_tts_service.py
speech_server/tts_services/kokoro_tts_service.py
speech_server-0.1.1.dist-info/LICENSE
speech_server-0.1.1.dist-info/METADATA
speech_server-0.1.1.dist-info/WHEEL
speech_server-0.1.1.dist-info/entry_points.txt
speech_server-0.1.1.dist-info/RECORD
