Metadata-Version: 2.1
Name: speech-server
Version: 0.1.1
Summary: FastAPI wrapper for Chatterbox TTS
Home-page: https://github.com/Ladvien/speech_server.git
Keywords: speech,tts,fastapi,chatterbox-tts,kokoro-onnx
Author: C. Thomas Brittain
Requires-Python: >=3.10,<3.13
Classifier: Programming Language :: Python :: 3
Classifier: Programming Language :: Python :: 3.10
Classifier: Programming Language :: Python :: 3.11
Classifier: Programming Language :: Python :: 3.12
Requires-Dist: aiofiles (>=23.2.0,<24.0.0)
Requires-Dist: chatterbox-tts (>=0.1.1,<0.2.0)
Requires-Dist: fastapi (>=0.104.1,<0.105.0)
Requires-Dist: httpx (>=0.25.2,<0.26.0)
Requires-Dist: kokoro-onnx (>=0.4.0,<0.5.0)
Requires-Dist: numpy (>=2.0.2,<3.0.0)
Requires-Dist: poethepoet (>=0.32.2,<0.33.0)
Requires-Dist: pyaudio (>=0.2.14,<0.3.0)
Requires-Dist: pydantic (>=2.5.0,<3.0.0)
Requires-Dist: python-multipart (>=0.0.6,<0.0.7)
Requires-Dist: pyyaml (>=6.0.2,<7.0.0)
Requires-Dist: rich (>=13.7.0,<14.0.0)
Requires-Dist: setuptools (>=80.9.0,<81.0.0)
Requires-Dist: sounddevice (>=0.5.1,<0.6.0)
Requires-Dist: soundfile (>=0.12.0,<0.13.0)
Requires-Dist: torch (>=2.1.0,<3.0.0)
Requires-Dist: torchaudio (>=2.1.0,<3.0.0)
Requires-Dist: uvicorn[standard] (>=0.24.0,<0.25.0)
Project-URL: Repository, https://github.com/Ladvien/speech_server.git
